{
    "count": 4,
    "data": [
        {
            "count": 2,
            "package": "Lcom/github/mikephil/charting/charts",
            "present": true
        },
        {
            "count": 2,
            "package": "Lcom/github/mikephil/charting",
            "present": true
        },
        {
            "count": 2,
            "package": "Lcom/github/mikephil",
            "present": true
        },
        {
            "count": 2,
            "package": "Lcom/github/mikephil/charting/c",
            "present": true
        }
    ],
    "filename": "../../outapks/fourrrrrrrr3157518&n.apk"
}